{
	"id": "3fac9b2b-f69d-445a-8380-aac87fc84b95",
	"name": "ContactBook_Env",
	"values": [
		{
			"key": "API_URL",
			"value": "http://localhost:5294/api/",
			"type": "default",
			"enabled": true
		},
		{
			"key": "countryId",
			"value": "1",
			"type": "default",
			"enabled": true
		},
		{
			"key": "uniqueId",
			"value": "",
			"type": "any",
			"enabled": true
		},
		{
			"key": "uniqueloginId",
			"value": "",
			"type": "any",
			"enabled": true
		},
		{
			"key": "uniquefname",
			"value": "",
			"type": "any",
			"enabled": true
		},
		{
			"key": "uniquelname",
			"value": "",
			"type": "any",
			"enabled": true
		},
		{
			"key": "uniquephonenumber",
			"value": "",
			"type": "any",
			"enabled": true
		},
		{
			"key": "userId",
			"value": "",
			"type": "any",
			"enabled": true
		},
		{
			"key": "generatedfname",
			"value": "",
			"type": "any",
			"enabled": true
		},
		{
			"key": "generatedlname",
			"value": "",
			"type": "any",
			"enabled": true
		},
		{
			"key": "contactEmailId",
			"value": "",
			"type": "any",
			"enabled": true
		},
		{
			"key": "contactfname",
			"value": "",
			"type": "any",
			"enabled": true
		},
		{
			"key": "contactlname",
			"value": "",
			"type": "any",
			"enabled": true
		},
		{
			"key": "contactNumber",
			"value": "",
			"type": "any",
			"enabled": true
		},
		{
			"key": "contactAddress",
			"value": "",
			"type": "any",
			"enabled": true
		},
		{
			"key": "contactFavorite",
			"value": "",
			"type": "any",
			"enabled": true
		},
		{
			"key": "contactGender",
			"value": "",
			"type": "any",
			"enabled": true
		},
		{
			"key": "contactBirthDate",
			"value": "",
			"type": "any",
			"enabled": true
		},
		{
			"key": "stateId",
			"value": "",
			"type": "any",
			"enabled": true
		},
		{
			"key": "contactId",
			"value": "",
			"type": "any",
			"enabled": true
		},
		{
			"key": "page",
			"value": "",
			"type": "default",
			"enabled": true
		},
		{
			"key": "pageSize",
			"value": "",
			"type": "default",
			"enabled": true
		},
		{
			"key": "sortOrder",
			"value": "",
			"type": "default",
			"enabled": true
		},
		{
			"key": "search",
			"value": "",
			"type": "default",
			"enabled": true
		},
		{
			"key": "letter",
			"value": "",
			"type": "default",
			"enabled": true
		}
	],
	"_postman_variable_scope": "environment",
	"_postman_exported_at": "2024-09-04T05:16:28.129Z",
	"_postman_exported_using": "Postman/11.10.1"
}